{"__madarTsExtractorVersion":67,"__madarFileStem":"button","nodes":[{"id":"button","label":"button.tsx","file_type":"code","source_file":"/home/gowdaman/Projects/personal/rimuru-ai/packages/ui/src/components/button.tsx","source_location":"L1","layer":"base","provenance":[{"capability_id":"builtin:extract:typescript","stage":"extract","source_file":"/home/gowdaman/Projects/personal/rimuru-ai/packages/ui/src/components/button.tsx","source_location":"L1"}]},{"id":"button_buttonprops","label":"ButtonProps","file_type":"code","source_file":"/home/gowdaman/Projects/personal/rimuru-ai/packages/ui/src/components/button.tsx","source_location":"L5-L11","layer":"base","provenance":[{"capability_id":"builtin:extract:typescript","stage":"extract","source_file":"/home/gowdaman/Projects/personal/rimuru-ai/packages/ui/src/components/button.tsx","source_location":"L5"}],"snippet":"export interface ButtonProps\n  extends ComponentProps<typeof Kobalte>,\n    Pick<ComponentProps<\"button\">, \"class\" | \"classList\" | \"children\"> {\n  size?: \"small\" | \"normal\" | \"large\"\n  variant?: \"primary\" | \"secondary\" | \"ghost\"\n  icon?: IconProps[\"name\"]\n}"},{"id":"button_componentprops","label":"ComponentProps","file_type":"code","source_file":"/home/gowdaman/Projects/personal/rimuru-ai/packages/ui/src/components/button.tsx","source_location":"L5","layer":"base","provenance":[{"capability_id":"builtin:extract:typescript","stage":"extract","source_file":"/home/gowdaman/Projects/personal/rimuru-ai/packages/ui/src/components/button.tsx","source_location":"L5"}]},{"id":"button_pick","label":"Pick","file_type":"code","source_file":"/home/gowdaman/Projects/personal/rimuru-ai/packages/ui/src/components/button.tsx","source_location":"L5","layer":"base","provenance":[{"capability_id":"builtin:extract:typescript","stage":"extract","source_file":"/home/gowdaman/Projects/personal/rimuru-ai/packages/ui/src/components/button.tsx","source_location":"L5"}]},{"id":"button_button","label":"Button()","file_type":"code","source_file":"/home/gowdaman/Projects/personal/rimuru-ai/packages/ui/src/components/button.tsx","source_location":"L13-L33","layer":"base","provenance":[{"capability_id":"builtin:extract:typescript","stage":"extract","source_file":"/home/gowdaman/Projects/personal/rimuru-ai/packages/ui/src/components/button.tsx","source_location":"L13"}],"snippet":"export function Button(props: ButtonProps) {\n  const [split, rest] = splitProps(props, [\"variant\", \"size\", \"icon\", \"class\", \"classList\"])\n  return (\n    <Kobalte\n      {...rest}\n      data-component=\"button\"\n      data-size={split.size || \"normal\"}\n      data-variant={split.variant || \"secondary\"}\n      data-icon={split.icon}\n      classList={{\n        ...split.classList,\n        [split.class ?? \"\"]: !!split.class,\n      }}\n    >\n      <Show when={split.icon}>\n        <Icon name={split.icon!} size=\"small\" />\n      </Show>\n      {props.children}\n    </Kobalte>\n  )\n}","node_kind":"component"}],"edges":[{"source":"button","target":"button","relation":"imports_from","confidence":"EXTRACTED","source_file":"/home/gowdaman/Projects/personal/rimuru-ai/packages/ui/src/components/button.tsx","source_location":"L1","layer":"base","provenance":[{"capability_id":"builtin:extract:typescript","stage":"extract","source_file":"/home/gowdaman/Projects/personal/rimuru-ai/packages/ui/src/components/button.tsx","source_location":"L1"}],"weight":1},{"source":"button","target":"solid_js","relation":"imports_from","confidence":"EXTRACTED","source_file":"/home/gowdaman/Projects/personal/rimuru-ai/packages/ui/src/components/button.tsx","source_location":"L2","layer":"base","provenance":[{"capability_id":"builtin:extract:typescript","stage":"extract","source_file":"/home/gowdaman/Projects/personal/rimuru-ai/packages/ui/src/components/button.tsx","source_location":"L2"}],"weight":1},{"source":"button","target":"icon","relation":"imports_from","confidence":"EXTRACTED","source_file":"/home/gowdaman/Projects/personal/rimuru-ai/packages/ui/src/components/button.tsx","source_location":"L3","layer":"base","provenance":[{"capability_id":"builtin:extract:typescript","stage":"extract","source_file":"/home/gowdaman/Projects/personal/rimuru-ai/packages/ui/src/components/button.tsx","source_location":"L3"}],"weight":1},{"source":"button","target":"button_buttonprops","relation":"contains","confidence":"EXTRACTED","source_file":"/home/gowdaman/Projects/personal/rimuru-ai/packages/ui/src/components/button.tsx","source_location":"L5","layer":"base","provenance":[{"capability_id":"builtin:extract:typescript","stage":"extract","source_file":"/home/gowdaman/Projects/personal/rimuru-ai/packages/ui/src/components/button.tsx","source_location":"L5"}],"weight":1},{"source":"button_buttonprops","target":"button_componentprops","relation":"inherits","confidence":"EXTRACTED","source_file":"/home/gowdaman/Projects/personal/rimuru-ai/packages/ui/src/components/button.tsx","source_location":"L5","layer":"base","provenance":[{"capability_id":"builtin:extract:typescript","stage":"extract","source_file":"/home/gowdaman/Projects/personal/rimuru-ai/packages/ui/src/components/button.tsx","source_location":"L5"}],"weight":1},{"source":"button_buttonprops","target":"button_pick","relation":"inherits","confidence":"EXTRACTED","source_file":"/home/gowdaman/Projects/personal/rimuru-ai/packages/ui/src/components/button.tsx","source_location":"L5","layer":"base","provenance":[{"capability_id":"builtin:extract:typescript","stage":"extract","source_file":"/home/gowdaman/Projects/personal/rimuru-ai/packages/ui/src/components/button.tsx","source_location":"L5"}],"weight":1},{"source":"button","target":"button_button","relation":"contains","confidence":"EXTRACTED","source_file":"/home/gowdaman/Projects/personal/rimuru-ai/packages/ui/src/components/button.tsx","source_location":"L13","layer":"base","provenance":[{"capability_id":"builtin:extract:typescript","stage":"extract","source_file":"/home/gowdaman/Projects/personal/rimuru-ai/packages/ui/src/components/button.tsx","source_location":"L13"}],"weight":1},{"source":"button_button","target":"Kobalte__jsx_proxy","relation":"renders","confidence":"EXTRACTED","source_file":"/home/gowdaman/Projects/personal/rimuru-ai/packages/ui/src/components/button.tsx","source_location":"L13","layer":"base","provenance":[{"capability_id":"builtin:extract:typescript","stage":"extract","source_file":"/home/gowdaman/Projects/personal/rimuru-ai/packages/ui/src/components/button.tsx","source_location":"L13"}],"weight":1},{"source":"button_button","target":"Show__jsx_proxy","relation":"renders","confidence":"EXTRACTED","source_file":"/home/gowdaman/Projects/personal/rimuru-ai/packages/ui/src/components/button.tsx","source_location":"L13","layer":"base","provenance":[{"capability_id":"builtin:extract:typescript","stage":"extract","source_file":"/home/gowdaman/Projects/personal/rimuru-ai/packages/ui/src/components/button.tsx","source_location":"L13"}],"weight":1},{"source":"button_button","target":"Icon__jsx_proxy","relation":"renders","confidence":"EXTRACTED","source_file":"/home/gowdaman/Projects/personal/rimuru-ai/packages/ui/src/components/button.tsx","source_location":"L13","layer":"base","provenance":[{"capability_id":"builtin:extract:typescript","stage":"extract","source_file":"/home/gowdaman/Projects/personal/rimuru-ai/packages/ui/src/components/button.tsx","source_location":"L13"}],"weight":1}]}