{"__madarTsExtractorVersion":67,"__madarFileStem":"packages_core_src_project","nodes":[{"id":"packages_core_src_project","label":"project.ts","file_type":"code","source_file":"/home/gowdaman/Projects/personal/rimuru-ai/packages/core/src/project.ts","source_location":"L1","layer":"base","provenance":[{"capability_id":"builtin:extract:typescript","stage":"extract","source_file":"/home/gowdaman/Projects/personal/rimuru-ai/packages/core/src/project.ts","source_location":"L1"}]},{"id":"packages_core_src_project_info","label":"Info","file_type":"code","source_file":"/home/gowdaman/Projects/personal/rimuru-ai/packages/core/src/project.ts","source_location":"L20-L22","layer":"base","provenance":[{"capability_id":"builtin:extract:typescript","stage":"extract","source_file":"/home/gowdaman/Projects/personal/rimuru-ai/packages/core/src/project.ts","source_location":"L20"}],"snippet":"export class Info extends Schema.Class<Info>(\"Project.Info\")({\n  id: ID,\n}) {}"},{"id":"packages_core_src_project_class","label":"Class","file_type":"code","source_file":"/home/gowdaman/Projects/personal/rimuru-ai/packages/core/src/project.ts","source_location":"L20","layer":"base","provenance":[{"capability_id":"builtin:extract:typescript","stage":"extract","source_file":"/home/gowdaman/Projects/personal/rimuru-ai/packages/core/src/project.ts","source_location":"L20"}]},{"id":"packages_core_src_project_resolved","label":"Resolved","file_type":"code","source_file":"/home/gowdaman/Projects/personal/rimuru-ai/packages/core/src/project.ts","source_location":"L30-L35","layer":"base","provenance":[{"capability_id":"builtin:extract:typescript","stage":"extract","source_file":"/home/gowdaman/Projects/personal/rimuru-ai/packages/core/src/project.ts","source_location":"L30"}],"snippet":"export interface Resolved {\n  readonly previous?: ID\n  readonly id: ID\n  readonly directory: AbsolutePath\n  readonly vcs?: Vcs\n}"},{"id":"packages_core_src_project_interface","label":"Interface","file_type":"code","source_file":"/home/gowdaman/Projects/personal/rimuru-ai/packages/core/src/project.ts","source_location":"L37-L50","layer":"base","provenance":[{"capability_id":"builtin:extract:typescript","stage":"extract","source_file":"/home/gowdaman/Projects/personal/rimuru-ai/packages/core/src/project.ts","source_location":"L37"}],"snippet":"export interface Interface {\n  readonly directories: (input: DirectoriesInput) => Effect.Effect<Directories>\n  readonly resolve: (input: AbsolutePath) => Effect.Effect<Resolved>\n  /**\n   * Temporary bridge method for writing the resolved project ID to the repo-local cache.\n   *\n   * This exists while the old opencode project service and this core project\n   * service work together: core resolves the ID, while the old service still owns\n   * database migration and persistence. The old service should call this after it\n   * finishes migrating from `resolve().previous` to `resolve().id`; once project\n   * persistence moves into core, this separate bridge method can go away.\n   */\n  readonly commit: (input: { store: AbsolutePath; id: ID }) => Effect.Effect<void>\n}"},{"id":"packages_core_src_project_service","label":"Service","file_type":"code","source_file":"/home/gowdaman/Projects/personal/rimuru-ai/packages/core/src/project.ts","source_location":"L52","layer":"base","provenance":[{"capability_id":"builtin:extract:typescript","stage":"extract","source_file":"/home/gowdaman/Projects/personal/rimuru-ai/packages/core/src/project.ts","source_location":"L52"}],"snippet":"export class Service extends Context.Service<Service, Interface>()(\"@opencode/ProjectV2\") {}"}],"edges":[{"source":"packages_core_src_project","target":"project","relation":"imports_from","confidence":"EXTRACTED","source_file":"/home/gowdaman/Projects/personal/rimuru-ai/packages/core/src/project.ts","source_location":"L1","layer":"base","provenance":[{"capability_id":"builtin:extract:typescript","stage":"extract","source_file":"/home/gowdaman/Projects/personal/rimuru-ai/packages/core/src/project.ts","source_location":"L1"}],"weight":1},{"source":"packages_core_src_project","target":"effect","relation":"imports_from","confidence":"EXTRACTED","source_file":"/home/gowdaman/Projects/personal/rimuru-ai/packages/core/src/project.ts","source_location":"L4","layer":"base","provenance":[{"capability_id":"builtin:extract:typescript","stage":"extract","source_file":"/home/gowdaman/Projects/personal/rimuru-ai/packages/core/src/project.ts","source_location":"L4"}],"weight":1},{"source":"packages_core_src_project","target":"path","relation":"imports_from","confidence":"EXTRACTED","source_file":"/home/gowdaman/Projects/personal/rimuru-ai/packages/core/src/project.ts","source_location":"L5","layer":"base","provenance":[{"capability_id":"builtin:extract:typescript","stage":"extract","source_file":"/home/gowdaman/Projects/personal/rimuru-ai/packages/core/src/project.ts","source_location":"L5"}],"weight":1},{"source":"packages_core_src_project","target":"schema","relation":"imports_from","confidence":"EXTRACTED","source_file":"/home/gowdaman/Projects/personal/rimuru-ai/packages/core/src/project.ts","source_location":"L6","layer":"base","provenance":[{"capability_id":"builtin:extract:typescript","stage":"extract","source_file":"/home/gowdaman/Projects/personal/rimuru-ai/packages/core/src/project.ts","source_location":"L6"}],"weight":1},{"source":"packages_core_src_project","target":"fs_util","relation":"imports_from","confidence":"EXTRACTED","source_file":"/home/gowdaman/Projects/personal/rimuru-ai/packages/core/src/project.ts","source_location":"L7","layer":"base","provenance":[{"capability_id":"builtin:extract:typescript","stage":"extract","source_file":"/home/gowdaman/Projects/personal/rimuru-ai/packages/core/src/project.ts","source_location":"L7"}],"weight":1},{"source":"packages_core_src_project","target":"git","relation":"imports_from","confidence":"EXTRACTED","source_file":"/home/gowdaman/Projects/personal/rimuru-ai/packages/core/src/project.ts","source_location":"L8","layer":"base","provenance":[{"capability_id":"builtin:extract:typescript","stage":"extract","source_file":"/home/gowdaman/Projects/personal/rimuru-ai/packages/core/src/project.ts","source_location":"L8"}],"weight":1},{"source":"packages_core_src_project","target":"layer_node","relation":"imports_from","confidence":"EXTRACTED","source_file":"/home/gowdaman/Projects/personal/rimuru-ai/packages/core/src/project.ts","source_location":"L9","layer":"base","provenance":[{"capability_id":"builtin:extract:typescript","stage":"extract","source_file":"/home/gowdaman/Projects/personal/rimuru-ai/packages/core/src/project.ts","source_location":"L9"}],"weight":1},{"source":"packages_core_src_project","target":"hash","relation":"imports_from","confidence":"EXTRACTED","source_file":"/home/gowdaman/Projects/personal/rimuru-ai/packages/core/src/project.ts","source_location":"L10","layer":"base","provenance":[{"capability_id":"builtin:extract:typescript","stage":"extract","source_file":"/home/gowdaman/Projects/personal/rimuru-ai/packages/core/src/project.ts","source_location":"L10"}],"weight":1},{"source":"packages_core_src_project","target":"directories","relation":"imports_from","confidence":"EXTRACTED","source_file":"/home/gowdaman/Projects/personal/rimuru-ai/packages/core/src/project.ts","source_location":"L11","layer":"base","provenance":[{"capability_id":"builtin:extract:typescript","stage":"extract","source_file":"/home/gowdaman/Projects/personal/rimuru-ai/packages/core/src/project.ts","source_location":"L11"}],"weight":1},{"source":"packages_core_src_project","target":"packages_core_src_project_info","relation":"contains","confidence":"EXTRACTED","source_file":"/home/gowdaman/Projects/personal/rimuru-ai/packages/core/src/project.ts","source_location":"L20","layer":"base","provenance":[{"capability_id":"builtin:extract:typescript","stage":"extract","source_file":"/home/gowdaman/Projects/personal/rimuru-ai/packages/core/src/project.ts","source_location":"L20"}],"weight":1},{"source":"packages_core_src_project_info","target":"packages_core_src_project_class","relation":"inherits","confidence":"EXTRACTED","source_file":"/home/gowdaman/Projects/personal/rimuru-ai/packages/core/src/project.ts","source_location":"L20","layer":"base","provenance":[{"capability_id":"builtin:extract:typescript","stage":"extract","source_file":"/home/gowdaman/Projects/personal/rimuru-ai/packages/core/src/project.ts","source_location":"L20"}],"weight":1},{"source":"packages_core_src_project","target":"packages_core_src_project_resolved","relation":"contains","confidence":"EXTRACTED","source_file":"/home/gowdaman/Projects/personal/rimuru-ai/packages/core/src/project.ts","source_location":"L30","layer":"base","provenance":[{"capability_id":"builtin:extract:typescript","stage":"extract","source_file":"/home/gowdaman/Projects/personal/rimuru-ai/packages/core/src/project.ts","source_location":"L30"}],"weight":1},{"source":"packages_core_src_project","target":"packages_core_src_project_interface","relation":"contains","confidence":"EXTRACTED","source_file":"/home/gowdaman/Projects/personal/rimuru-ai/packages/core/src/project.ts","source_location":"L37","layer":"base","provenance":[{"capability_id":"builtin:extract:typescript","stage":"extract","source_file":"/home/gowdaman/Projects/personal/rimuru-ai/packages/core/src/project.ts","source_location":"L37"}],"weight":1},{"source":"packages_core_src_project","target":"packages_core_src_project_service","relation":"contains","confidence":"EXTRACTED","source_file":"/home/gowdaman/Projects/personal/rimuru-ai/packages/core/src/project.ts","source_location":"L52","layer":"base","provenance":[{"capability_id":"builtin:extract:typescript","stage":"extract","source_file":"/home/gowdaman/Projects/personal/rimuru-ai/packages/core/src/project.ts","source_location":"L52"}],"weight":1},{"source":"packages_core_src_project_service","target":"packages_core_src_project_service","relation":"inherits","confidence":"EXTRACTED","source_file":"/home/gowdaman/Projects/personal/rimuru-ai/packages/core/src/project.ts","source_location":"L52","layer":"base","provenance":[{"capability_id":"builtin:extract:typescript","stage":"extract","source_file":"/home/gowdaman/Projects/personal/rimuru-ai/packages/core/src/project.ts","source_location":"L52"}],"weight":1}]}